{"queries":[{"Query":{"Commands":[{"SemanticQueryDataShapeCommand":{"Query":{"Version":2,"From":[{"Name":"s","Entity":"SQLSales2008"},{"Name":"s1","Entity":"StatesPopulation"}],"Select":[{"Column":{"Expression":{"SourceRef":{"Source":"s"}},"Property":"CountryName"},"Name":"SQLSales2008.CountryName"},{"Column":{"Expression":{"SourceRef":{"Source":"s"}},"Property":"CountryShortName"},"Name":"SQLSales2008.CountryShortName"},{"Aggregation":{"Expression":{"Column":{"Expression":{"SourceRef":{"Source":"s"}},"Property":"Sales"}},"Function":0},"Name":"Sum(SQLSales2008.Sales)"},{"Aggregation":{"Expression":{"Column":{"Expression":{"SourceRef":{"Source":"s1"}},"Property":"area"}},"Function":0},"Name":"Sum(StatesPopulation.area)"},{"Aggregation":{"Expression":{"Column":{"Expression":{"SourceRef":{"Source":"s1"}},"Property":"HomeSales"}},"Function":0},"Name":"Sum(StatesPopulation.HomeSales)"},{"Aggregation":{"Expression":{"Column":{"Expression":{"SourceRef":{"Source":"s1"}},"Property":"population"}},"Function":0},"Name":"Sum(StatesPopulation.population)"}]},"Binding":{"Primary":{"Groupings":[{"Projections":[0,1,2,3,4,5],"Subtotal":1}]},"DataReduction":{"DataVolume":3,"Primary":{"Window":{"Count":500}}},"Version":1}}}]}}],"modelId":"890348772"}